codeguru_profiler_agent/__init__.py
codeguru_profiler_agent/__main__.py
codeguru_profiler_agent/codeguru_client_builder.py
codeguru_profiler_agent/local_aggregator.py
codeguru_profiler_agent/profiler.py
codeguru_profiler_agent/profiler_builder.py
codeguru_profiler_agent/profiler_disabler.py
codeguru_profiler_agent/profiler_runner.py
codeguru_profiler_agent/sampler.py
codeguru_profiler_agent/sampling_utils.py
codeguru_profiler_agent/agent_metadata/__init__.py
codeguru_profiler_agent/agent_metadata/agent_debug_info.py
codeguru_profiler_agent/agent_metadata/agent_metadata.py
codeguru_profiler_agent/agent_metadata/aws_ec2_instance.py
codeguru_profiler_agent/agent_metadata/aws_fargate_task.py
codeguru_profiler_agent/agent_metadata/aws_lambda.py
codeguru_profiler_agent/agent_metadata/fleet_info.py
codeguru_profiler_agent/aws_lambda/__init__.py
codeguru_profiler_agent/aws_lambda/lambda_context.py
codeguru_profiler_agent/aws_lambda/lambda_handler.py
codeguru_profiler_agent/aws_lambda/profiler_decorator.py
codeguru_profiler_agent/file_reporter/__init__.py
codeguru_profiler_agent/file_reporter/file_reporter.py
codeguru_profiler_agent/metrics/__init__.py
codeguru_profiler_agent/metrics/metric.py
codeguru_profiler_agent/metrics/timer.py
codeguru_profiler_agent/metrics/with_timer.py
codeguru_profiler_agent/model/__init__.py
codeguru_profiler_agent/model/call_graph_node.py
codeguru_profiler_agent/model/frame.py
codeguru_profiler_agent/model/memory_counter.py
codeguru_profiler_agent/model/profile.py
codeguru_profiler_agent/model/sample.py
codeguru_profiler_agent/reporter/__init__.py
codeguru_profiler_agent/reporter/agent_configuration.py
codeguru_profiler_agent/reporter/reporter.py
codeguru_profiler_agent/sdk_reporter/__init__.py
codeguru_profiler_agent/sdk_reporter/profile_encoder.py
codeguru_profiler_agent/sdk_reporter/sdk_reporter.py
codeguru_profiler_agent/utils/__init__.py
codeguru_profiler_agent/utils/execution_state.py
codeguru_profiler_agent/utils/log_exception.py
codeguru_profiler_agent-1.2.6.dist-info/licenses/LICENSE
codeguru_profiler_agent-1.2.6.dist-info/licenses/NOTICE
codeguru_profiler_agent-1.2.6.dist-info/METADATA
codeguru_profiler_agent-1.2.6.dist-info/WHEEL
codeguru_profiler_agent-1.2.6.dist-info/top_level.txt
codeguru_profiler_agent-1.2.6.dist-info/RECORD
